Workbook
Name Slicer_Location: #N/A
Name Slicer_Product_type: #N/A

Sheet Raw_Data 
A1: Product type | B1: SKU | C1: Price | D1: Availability | E1: Number of products sold | F1: Revenue generated | G1: Customer demographics | H1: Stock levels | I1: Lead times | J1: Order quantities | K1: Shipping times | L1: Shipping carriers | M1: Shipping costs | N1: Supplier name | O1: Location | P1: Lead time | Q1: Production volumes | R1: Manufacturing lead time | S1: Manufacturing costs | T1: Inspection results | U1: Defect rates | V1: Transportation modes | W1: Routes | X1: Costs
A2: haircare | B2: SKU0 | C2: 69.808006 | D2: 55 | E2: 802 | F2: 8661.9968 | G2: Non-binary | H2: 58 | I2: 7 | J2: 96 | K2: 4 | L2: Carrier B | M2: 2.9565721 | N2: Supplier 3 | O2: Mumbai | P2: 29 | Q2: 215 | R2: 29 | S2: 46.279879 | T2: Pending | U2: 0.22641036 | V2: Road | W2: Route B | X2: 187.75208
A3: skincare | B3: SKU1 | C3: 14.843523 | D3: 95 | E3: 736 | F3: 7460.9001 | G3: Female | H3: 53 | I3: 30 | J3: 37 | K3: 2 | L3: Carrier A | M3: 9.7165748 | N3: Supplier 3 | O3: Mumbai | P3: 23 | Q3: 517 | R3: 30 | S3: 33.616769 | T3: Pending | U3: 4.854068 | V3: Road | W3: Route B | X3: 503.06558
A4: haircare | B4: SKU2 | C4: 11.319683 | D4: 34 | E4: 8 | F4: 9577.7496 | G4: Unknown | H4: 1 | I4: 10 | J4: 88 | K4: 2 | L4: Carrier B | M4: 8.0544793 | N4: Supplier 1 | O4: Mumbai | P4: 12 | Q4: 971 | R4: 27 | S4: 30.688019 | T4: Pending | U4: 4.5805926 | V4: Air | W4: Route C | X4: 141.92028
A5: skincare | B5: SKU3 | C5: 61.163343 | D5: 68 | E5: 83 | F5: 7766.8364 | G5: Non-binary | H5: 23 | I5: 13 | J5: 59 | K5: 6 | L5: Carrier C | M5: 1.7295686 | N5: Supplier 5 | O5: Kolkata | P5: 24 | Q5: 937 | R5: 18 | S5: 35.624741 | T5: Fail | U5: 4.7466486 | V5: Rail | W5: Route A | X5: 254.77616
A6: skincare | B6: SKU4 | C6: 4.805496 | D6: 26 | E6: 871 | F6: 2686.5052 | G6: Non-binary | H6: 5 | I6: 3 | J6: 56 | K6: 8 | L6: Carrier A | M6: 3.8905479 | N6: Supplier 1 | O6: Delhi | P6: 5 | Q6: 414 | R6: 3 | S6: 92.065161 | T6: Fail | U6: 3.1455795 | V6: Air | W6: Route A | X6: 923.44063
A7: haircare | B7: SKU5 | C7: 1.699976 | D7: 87 | E7: 147 | F7: 2828.3487 | G7: Non-binary | H7: 90 | I7: 27 | J7: 66 | K7: 3 | L7: Carrier B | M7: 4.4440989 | N7: Supplier 4 | O7: Bangalore | P7: 10 | Q7: 104 | R7: 17 | S7: 56.766476 | T7: Fail | U7: 2.7791935 | V7: Road | W7: Route A | X7: 235.46124
A8: skincare | B8: SKU6 | C8: 4.0783329 | D8: 48 | E8: 65 | F8: 7823.4766 | G8: Male | H8: 11 | I8: 15 | J8: 58 | K8: 8 | L8: Carrier C | M8: 3.8807633 | N8: Supplier 3 | O8: Kolkata | P8: 14 | Q8: 314 | R8: 24 | S8: 1.0850686 | T8: Pending | U8: 1.0009106 | V8: Sea | W8: Route A | X8: 134.3691
A9: cosmetics | B9: SKU7 | C9: 42.958384 | D9: 59 | E9: 426 | F9: 8496.1038 | G9: Female | H9: 93 | I9: 17 | J9: 11 | K9: 1 | L9: Carrier B | M9: 2.3483388 | N9: Supplier 4 | O9: Bangalore | P9: 22 | Q9: 564 | R9: 1 | S9: 99.466109 | T9: Fail | U9: 0.39817719 | V9: Road | W9: Route C | X9: 802.05631
A10: cosmetics | B10: SKU8 | C10: 68.717597 | D10: 78 | E10: 150 | F10: 7517.3632 | G10: Female | H10: 5 | I10: 10 | J10: 15 | K10: 7 | L10: Carrier C | M10: 3.4047339 | N10: Supplier 4 | O10: Mumbai | P10: 13 | Q10: 769 | R10: 8 | S10: 11.423027 | T10: Pending | U10: 2.7098627 | V10: Sea | W10: Route B | X10: 505.55713
A11: skincare | B11: SKU9 | C11: 64.015733 | D11: 35 | E11: 980 | F11: 4971.146 | G11: Unknown | H11: 14 | I11: 27 | J11: 83 | K11: 1 | L11: Carrier A | M11: 7.1666453 | N11: Supplier 2 | O11: Chennai | P11: 29 | Q11: 963 | R11: 23 | S11: 47.957602 | T11: Pending | U11: 3.8446145 | V11: Rail | W11: Route B | X11: 995.92946
A12: skincare | B12: SKU10 | C12: 15.707796 | D12: 11 | E12: 996 | F12: 2330.9658 | G12: Non-binary | H12: 51 | I12: 13 | J12: 80 | K12: 2 | L12: Carrier C | M12: 8.6732112 | N12: Supplier 5 | O12: Kolkata | P12: 18 | Q12: 830 | R12: 5 | S12: 96.527353 | T12: Pass | U12: 1.7273139 | V12: Road | W12: Route B | X12: 806.10318
A13: skincare | B13: SKU11 | C13: 90.63546 | D13: 95 | E13: 960 | F13: 6099.9441 | G13: Female | H13: 46 | I13: 23 | J13: 60 | K13: 1 | L13: Carrier A | M13: 4.5239431 | N13: Supplier 2 | O13: Kolkata | P13: 28 | Q13: 362 | R13: 11 | S13: 27.592363 | T13: Pending | U13: 0.021169821 | V13: Air | W13: Route A | X13: 126.72303
... A101: haircare | B101: SKU99 | C101: 68.517833 | D101: 17 | E101: 627 | F101: 9185.1858 | G101: Unknown | H101: 55 | I101: 8 | J101: 59 | K101: 6 | L101: Carrier B | M101: 1.3110238 | N101: Supplier 2 | O101: Chennai | P101: 29 | Q101: 921 | R101: 2 | S101: 38.072899 | T101: Fail | U101: 0.34602729 | V101: Rail | W101: Route B | X101: 210.74301

Sheet Data_Cleaning
A1: Product type | B1: SKU | C1: Price | D1: Availability | E1: Number_of_products sold | F1: Revenue_generated | G1: Customer_demographics | H1: Stock_levels | I1: Lead_times | J1: Order_quantities | K1: Shipping_times | L1: Shipping_carriers | M1: Shipping_costs | N1: Supplier_name | O1: Location | P1: Lead_time | Q1: Production_volumes | R1: Manufacturing_lead_time | S1: Manufacturing_costs | T1: Inspection results | U1: Defect_rates | V1: Transportation modes | W1: Routes | X1: Costs | Y1: Revenue per Unit | Z1: Inventory_Status | AA1: Lead_Time_Category | AB1: Defect_Status | AC1: Estimated_Manufacturing_Cost | AD1: Estimated_Shipping_Cost | AE1: Estimated_Profit/Loss
A2: haircare | B2: SKU0 | C2: 69.808006 | D2: 55 | E2: 802 | F2: 8661.9968 | G2: Non-binary | H2: 58 | I2: 7 | J2: 96 | K2: 4 | L2: Carrier B | M2: 2.9565721 | N2: Supplier 3 | O2: Mumbai | P2: 29 | Q2: 215 | R2: 29 | S2: 46.279879 | T2: Pending | U2: 0.22641036 | V2: Road | W2: Route B | X2: 187.75208 | Y2: =supply_chain_data4[[#This Row],[Revenue_generated ]]/supply_chain_data4[[#This Row],[Number_of_products sold]] -> 10.800495 | Z2: =IF(supply_chain_data4[[#This Row],[Stock_levels]]<30,"Low Stock", IF(supply_chain_data4[[#This Row],[Stock_levels]]<=70,"Medium Stock","High Stock")) -> Medium Stock | AA2: =IF(supply_chain_data4[[#This Row],[Lead_time]]<=10,"Short", IF(supply_chain_data4[[#This Row],[Lead_time]]<=20,"Medium","Long")) -> Long | AB2: =IF(supply_chain_data4[[#This Row],[Defect_rates]]<2,"Low Defect", IF(supply_chain_data4[[#This Row],[Defect_rates]]<=4,"Medium Defect","High Defect")) -> Low Defect | AC2: =supply_chain_data4[[#This Row],[Production_volumes]]*supply_chain_data4[[#This Row],[Manufacturing_costs]] -> 9950.174 | AD2: =supply_chain_data4[[#This Row],[Order_quantities]]*supply_chain_data4[[#This Row],[Shipping_costs]] -> 283.83093 | AE2: =supply_chain_data4[[#This Row],[Revenue_generated ]]-AC2-AD2 -> -1572.0082
A3: skincare | B3: SKU1 | C3: 14.843523 | D3: 95 | E3: 736 | F3: 7460.9001 | G3: Female | H3: 53 | I3: 30 | J3: 37 | K3: 2 | L3: Carrier A | M3: 9.7165748 | N3: Supplier 3 | O3: Mumbai | P3: 23 | Q3: 517 | R3: 30 | S3: 33.616769 | T3: Pending | U3: 4.854068 | V3: Road | W3: Route B | X3: 503.06558 | Y3: =supply_chain_data4[[#This Row],[Revenue_generated ]]/supply_chain_data4[[#This Row],[Number_of_products sold]] -> 10.137092 | Z3: =IF(supply_chain_data4[[#This Row],[Stock_levels]]<30,"Low Stock", IF(supply_chain_data4[[#This Row],[Stock_levels]]<=70,"Medium Stock","High Stock")) -> Medium Stock | AA3: =IF(supply_chain_data4[[#This Row],[Lead_time]]<=10,"Short", IF(supply_chain_data4[[#This Row],[Lead_time]]<=20,"Medium","Long")) -> Long | AB3: =IF(supply_chain_data4[[#This Row],[Defect_rates]]<2,"Low Defect", IF(supply_chain_data4[[#This Row],[Defect_rates]]<=4,"Medium Defect","High Defect")) -> High Defect | AC3: =supply_chain_data4[[#This Row],[Production_volumes]]*supply_chain_data4[[#This Row],[Manufacturing_costs]] -> 17379.87 | AD3: =supply_chain_data4[[#This Row],[Order_quantities]]*supply_chain_data4[[#This Row],[Shipping_costs]] -> 359.51327 | AE3: =supply_chain_data4[[#This Row],[Revenue_generated ]]-AC3-AD3 -> -10278.483
A4: haircare | B4: SKU2 | C4: 11.319683 | D4: 34 | E4: 8 | F4: 9577.7496 | G4: Unknown | H4: 1 | I4: 10 | J4: 88 | K4: 2 | L4: Carrier B | M4: 8.0544793 | N4: Supplier 1 | O4: Mumbai | P4: 12 | Q4: 971 | R4: 27 | S4: 30.688019 | T4: Pending | U4: 4.5805926 | V4: Air | W4: Route C | X4: 141.92028 | Y4: =supply_chain_data4[[#This Row],[Revenue_generated ]]/supply_chain_data4[[#This Row],[Number_of_products sold]] -> 1197.2187 | Z4: =IF(supply_chain_data4[[#This Row],[Stock_levels]]<30,"Low Stock", IF(supply_chain_data4[[#This Row],[Stock_levels]]<=70,"Medium Stock","High Stock")) -> Low Stock | AA4: =IF(supply_chain_data4[[#This Row],[Lead_time]]<=10,"Short", IF(supply_chain_data4[[#This Row],[Lead_time]]<=20,"Medium","Long")) -> Medium | AB4: =IF(supply_chain_data4[[#This Row],[Defect_rates]]<2,"Low Defect", IF(supply_chain_data4[[#This Row],[Defect_rates]]<=4,"Medium Defect","High Defect")) -> High Defect | AC4: =supply_chain_data4[[#This Row],[Production_volumes]]*supply_chain_data4[[#This Row],[Manufacturing_costs]] -> 29798.067 | AD4: =supply_chain_data4[[#This Row],[Order_quantities]]*supply_chain_data4[[#This Row],[Shipping_costs]] -> 708.79418 | AE4: =supply_chain_data4[[#This Row],[Revenue_generated ]]-AC4-AD4 -> -20929.111
A5: skincare | B5: SKU3 | C5: 61.163343 | D5: 68 | E5: 83 | F5: 7766.8364 | G5: Non-binary | H5: 23 | I5: 13 | J5: 59 | K5: 6 | L5: Carrier C | M5: 1.7295686 | N5: Supplier 5 | O5: Kolkata | P5: 24 | Q5: 937 | R5: 18 | S5: 35.624741 | T5: Fail | U5: 4.7466486 | V5: Rail | W5: Route A | X5: 254.77616 | Y5: =supply_chain_data4[[#This Row],[Revenue_generated ]]/supply_chain_data4[[#This Row],[Number_of_products sold]] -> 93.576342 | Z5: =IF(supply_chain_data4[[#This Row],[Stock_levels]]<30,"Low Stock", IF(supply_chain_data4[[#This Row],[Stock_levels]]<=70,"Medium Stock","High Stock")) -> Low Stock | AA5: =IF(supply_chain_data4[[#This Row],[Lead_time]]<=10,"Short", IF(supply_chain_data4[[#This Row],[Lead_time]]<=20,"Medium","Long")) -> Long | AB5: =IF(supply_chain_data4[[#This Row],[Defect_rates]]<2,"Low Defect", IF(supply_chain_data4[[#This Row],[Defect_rates]]<=4,"Medium Defect","High Defect")) -> High Defect | AC5: =supply_chain_data4[[#This Row],[Production_volumes]]*supply_chain_data4[[#This Row],[Manufacturing_costs]] -> 33380.383 | AD5: =supply_chain_data4[[#This Row],[Order_quantities]]*supply_chain_data4[[#This Row],[Shipping_costs]] -> 102.04455 | AE5: =supply_chain_data4[[#This Row],[Revenue_generated ]]-AC5-AD5 -> -25715.591
A6: skincare | B6: SKU4 | C6: 4.805496 | D6: 26 | E6: 871 | F6: 2686.5052 | G6: Non-binary | H6: 5 | I6: 3 | J6: 56 | K6: 8 | L6: Carrier A | M6: 3.8905479 | N6: Supplier 1 | O6: Delhi | P6: 5 | Q6: 414 | R6: 3 | S6: 92.065161 | T6: Fail | U6: 3.1455795 | V6: Air | W6: Route A | X6: 923.44063 | Y6: =supply_chain_data4[[#This Row],[Revenue_generated ]]/supply_chain_data4[[#This Row],[Number_of_products sold]] -> 3.0843917 | Z6: =IF(supply_chain_data4[[#This Row],[Stock_levels]]<30,"Low Stock", IF(supply_chain_data4[[#This Row],[Stock_levels]]<=70,"Medium Stock","High Stock")) -> Low Stock | AA6: =IF(supply_chain_data4[[#This Row],[Lead_time]]<=10,"Short", IF(supply_chain_data4[[#This Row],[Lead_time]]<=20,"Medium","Long")) -> Short | AB6: =IF(supply_chain_data4[[#This Row],[Defect_rates]]<2,"Low Defect", IF(supply_chain_data4[[#This Row],[Defect_rates]]<=4,"Medium Defect","High Defect")) -> Medium Defect | AC6: =supply_chain_data4[[#This Row],[Production_volumes]]*supply_chain_data4[[#This Row],[Manufacturing_costs]] -> 38114.976 | AD6: =supply_chain_data4[[#This Row],[Order_quantities]]*supply_chain_data4[[#This Row],[Shipping_costs]] -> 217.87068 | AE6: =supply_chain_data4[[#This Row],[Revenue_generated ]]-AC6-AD6 -> -35646.342
A7: haircare | B7: SKU5 | C7: 1.699976 | D7: 87 | E7: 147 | F7: 2828.3487 | G7: Non-binary | H7: 90 | I7: 27 | J7: 66 | K7: 3 | L7: Carrier B | M7: 4.4440989 | N7: Supplier 4 | O7: Bangalore | P7: 10 | Q7: 104 | R7: 17 | S7: 56.766476 | T7: Fail | U7: 2.7791935 | V7: Road | W7: Route A | X7: 235.46124 | Y7: =supply_chain_data4[[#This Row],[Revenue_generated ]]/supply_chain_data4[[#This Row],[Number_of_products sold]] -> 19.240468 | Z7: =IF(supply_chain_data4[[#This Row],[Stock_levels]]<30,"Low Stock", IF(supply_chain_data4[[#This Row],[Stock_levels]]<=70,"Medium Stock","High Stock")) -> High Stock | AA7: =IF(supply_chain_data4[[#This Row],[Lead_time]]<=10,"Short", IF(supply_chain_data4[[#This Row],[Lead_time]]<=20,"Medium","Long")) -> Short | AB7: =IF(supply_chain_data4[[#This Row],[Defect_rates]]<2,"Low Defect", IF(supply_chain_data4[[#This Row],[Defect_rates]]<=4,"Medium Defect","High Defect")) -> Medium Defect | AC7: =supply_chain_data4[[#This Row],[Production_volumes]]*supply_chain_data4[[#This Row],[Manufacturing_costs]] -> 5903.7135 | AD7: =supply_chain_data4[[#This Row],[Order_quantities]]*supply_chain_data4[[#This Row],[Shipping_costs]] -> 293.31053 | AE7: =supply_chain_data4[[#This Row],[Revenue_generated ]]-AC7-AD7 -> -3368.6752
A8: skincare | B8: SKU6 | C8: 4.0783329 | D8: 48 | E8: 65 | F8: 7823.4766 | G8: Male | H8: 11 | I8: 15 | J8: 58 | K8: 8 | L8: Carrier C | M8: 3.8807633 | N8: Supplier 3 | O8: Kolkata | P8: 14 | Q8: 314 | R8: 24 | S8: 1.0850686 | T8: Pending | U8: 1.0009106 | V8: Sea | W8: Route A | X8: 134.3691 | Y8: =supply_chain_data4[[#This Row],[Revenue_generated ]]/supply_chain_data4[[#This Row],[Number_of_products sold]] -> 120.36118 | Z8: =IF(supply_chain_data4[[#This Row],[Stock_levels]]<30,"Low Stock", IF(supply_chain_data4[[#This Row],[Stock_levels]]<=70,"Medium Stock","High Stock")) -> Low Stock | AA8: =IF(supply_chain_data4[[#This Row],[Lead_time]]<=10,"Short", IF(supply_chain_data4[[#This Row],[Lead_time]]<=20,"Medium","Long")) -> Medium | AB8: =IF(supply_chain_data4[[#This Row],[Defect_rates]]<2,"Low Defect", IF(supply_chain_data4[[#This Row],[Defect_rates]]<=4,"Medium Defect","High Defect")) -> Low Defect | AC8: =supply_chain_data4[[#This Row],[Production_volumes]]*supply_chain_data4[[#This Row],[Manufacturing_costs]] -> 340.71153 | AD8: =supply_chain_data4[[#This Row],[Order_quantities]]*supply_chain_data4[[#This Row],[Shipping_costs]] -> 225.08427 | AE8: =supply_chain_data4[[#This Row],[Revenue_generated ]]-AC8-AD8 -> 7257.6808
A9: cosmetics | B9: SKU7 | C9: 42.958384 | D9: 59 | E9: 426 | F9: 8496.1038 | G9: Female | H9: 93 | I9: 17 | J9: 11 | K9: 1 | L9: Carrier B | M9: 2.3483388 | N9: Supplier 4 | O9: Bangalore | P9: 22 | Q9: 564 | R9: 1 | S9: 99.466109 | T9: Fail | U9: 0.39817719 | V9: Road | W9: Route C | X9: 802.05631 | Y9: =supply_chain_data4[[#This Row],[Revenue_generated ]]/supply_chain_data4[[#This Row],[Number_of_products sold]] -> 19.943906 | Z9: =IF(supply_chain_data4[[#This Row],[Stock_levels]]<30,"Low Stock", IF(supply_chain_data4[[#This Row],[Stock_levels]]<=70,"Medium Stock","High Stock")) -> High Stock | AA9: =IF(supply_chain_data4[[#This Row],[Lead_time]]<=10,"Short", IF(supply_chain_data4[[#This Row],[Lead_time]]<=20,"Medium","Long")) -> Long | AB9: =IF(supply_chain_data4[[#This Row],[Defect_rates]]<2,"Low Defect", IF(supply_chain_data4[[#This Row],[Defect_rates]]<=4,"Medium Defect","High Defect")) -> Low Defect | AC9: =supply_chain_data4[[#This Row],[Production_volumes]]*supply_chain_data4[[#This Row],[Manufacturing_costs]] -> 56098.885 | AD9: =supply_chain_data4[[#This Row],[Order_quantities]]*supply_chain_data4[[#This Row],[Shipping_costs]] -> 25.831727 | AE9: =supply_chain_data4[[#This Row],[Revenue_generated ]]-AC9-AD9 -> -47628.613
A10: cosmetics | B10: SKU8 | C10: 68.717597 | D10: 78 | E10: 150 | F10: 7517.3632 | G10: Female | H10: 5 | I10: 10 | J10: 15 | K10: 7 | L10: Carrier C | M10: 3.4047339 | N10: Supplier 4 | O10: Mumbai | P10: 13 | Q10: 769 | R10: 8 | S10: 11.423027 | T10: Pending | U10: 2.7098627 | V10: Sea | W10: Route B | X10: 505.55713 | Y10: =supply_chain_data4[[#This Row],[Revenue_generated ]]/supply_chain_data4[[#This Row],[Number_of_products sold]] -> 50.115755 | Z10: =IF(supply_chain_data4[[#This Row],[Stock_levels]]<30,"Low Stock", IF(supply_chain_data4[[#This Row],[Stock_levels]]<=70,"Medium Stock","High Stock")) -> Low Stock | AA10: =IF(supply_chain_data4[[#This Row],[Lead_time]]<=10,"Short", IF(supply_chain_data4[[#This Row],[Lead_time]]<=20,"Medium","Long")) -> Medium | AB10: =IF(supply_chain_data4[[#This Row],[Defect_rates]]<2,"Low Defect", IF(supply_chain_data4[[#This Row],[Defect_rates]]<=4,"Medium Defect","High Defect")) -> Medium Defect | AC10: =supply_chain_data4[[#This Row],[Production_volumes]]*supply_chain_data4[[#This Row],[Manufacturing_costs]] -> 8784.3079 | AD10: =supply_chain_data4[[#This Row],[Order_quantities]]*supply_chain_data4[[#This Row],[Shipping_costs]] -> 51.071008 | AE10: =supply_chain_data4[[#This Row],[Revenue_generated ]]-AC10-AD10 -> -1318.0157
A11: skincare | B11: SKU9 | C11: 64.015733 | D11: 35 | E11: 980 | F11: 4971.146 | G11: Unknown | H11: 14 | I11: 27 | J11: 83 | K11: 1 | L11: Carrier A | M11: 7.1666453 | N11: Supplier 2 | O11: Chennai | P11: 29 | Q11: 963 | R11: 23 | S11: 47.957602 | T11: Pending | U11: 3.8446145 | V11: Rail | W11: Route B | X11: 995.92946 | Y11: =supply_chain_data4[[#This Row],[Revenue_generated ]]/supply_chain_data4[[#This Row],[Number_of_products sold]] -> 5.0725979 | Z11: =IF(supply_chain_data4[[#This Row],[Stock_levels]]<30,"Low Stock", IF(supply_chain_data4[[#This Row],[Stock_levels]]<=70,"Medium Stock","High Stock")) -> Low Stock | AA11: =IF(supply_chain_data4[[#This Row],[Lead_time]]<=10,"Short", IF(supply_chain_data4[[#This Row],[Lead_time]]<=20,"Medium","Long")) -> Long | AB11: =IF(supply_chain_data4[[#This Row],[Defect_rates]]<2,"Low Defect", IF(supply_chain_data4[[#This Row],[Defect_rates]]<=4,"Medium Defect","High Defect")) -> Medium Defect | AC11: =supply_chain_data4[[#This Row],[Production_volumes]]*supply_chain_data4[[#This Row],[Manufacturing_costs]] -> 46183.17 | AD11: =supply_chain_data4[[#This Row],[Order_quantities]]*supply_chain_data4[[#This Row],[Shipping_costs]] -> 594.83156 | AE11: =supply_chain_data4[[#This Row],[Revenue_generated ]]-AC11-AD11 -> -41806.856
A12: skincare | B12: SKU10 | C12: 15.707796 | D12: 11 | E12: 996 | F12: 2330.9658 | G12: Non-binary | H12: 51 | I12: 13 | J12: 80 | K12: 2 | L12: Carrier C | M12: 8.6732112 | N12: Supplier 5 | O12: Kolkata | P12: 18 | Q12: 830 | R12: 5 | S12: 96.527353 | T12: Pass | U12: 1.7273139 | V12: Road | W12: Route B | X12: 806.10318 | Y12: =supply_chain_data4[[#This Row],[Revenue_generated ]]/supply_chain_data4[[#This Row],[Number_of_products sold]] -> 2.3403271 | Z12: =IF(supply_chain_data4[[#This Row],[Stock_levels]]<30,"Low Stock", IF(supply_chain_data4[[#This Row],[Stock_levels]]<=70,"Medium Stock","High Stock")) -> Medium Stock | AA12: =IF(supply_chain_data4[[#This Row],[Lead_time]]<=10,"Short", IF(supply_chain_data4[[#This Row],[Lead_time]]<=20,"Medium","Long")) -> Medium | AB12: =IF(supply_chain_data4[[#This Row],[Defect_rates]]<2,"Low Defect", IF(supply_chain_data4[[#This Row],[Defect_rates]]<=4,"Medium Defect","High Defect")) -> Low Defect | AC12: =supply_chain_data4[[#This Row],[Production_volumes]]*supply_chain_data4[[#This Row],[Manufacturing_costs]] -> 80117.703 | AD12: =supply_chain_data4[[#This Row],[Order_quantities]]*supply_chain_data4[[#This Row],[Shipping_costs]] -> 693.8569 | AE12: =supply_chain_data4[[#This Row],[Revenue_generated ]]-AC12-AD12 -> -78480.594
A13: skincare | B13: SKU11 | C13: 90.63546 | D13: 95 | E13: 960 | F13: 6099.9441 | G13: Female | H13: 46 | I13: 23 | J13: 60 | K13: 1 | L13: Carrier A | M13: 4.5239431 | N13: Supplier 2 | O13: Kolkata | P13: 28 | Q13: 362 | R13: 11 | S13: 27.592363 | T13: Pending | U13: 0.021169821 | V13: Air | W13: Route A | X13: 126.72303 | Y13: =supply_chain_data4[[#This Row],[Revenue_generated ]]/supply_chain_data4[[#This Row],[Number_of_products sold]] -> 6.3541085 | Z13: =IF(supply_chain_data4[[#This Row],[Stock_levels]]<30,"Low Stock", IF(supply_chain_data4[[#This Row],[Stock_levels]]<=70,"Medium Stock","High Stock")) -> Medium Stock | AA13: =IF(supply_chain_data4[[#This Row],[Lead_time]]<=10,"Short", IF(supply_chain_data4[[#This Row],[Lead_time]]<=20,"Medium","Long")) -> Long | AB13: =IF(supply_chain_data4[[#This Row],[Defect_rates]]<2,"Low Defect", IF(supply_chain_data4[[#This Row],[Defect_rates]]<=4,"Medium Defect","High Defect")) -> Low Defect | AC13: =supply_chain_data4[[#This Row],[Production_volumes]]*supply_chain_data4[[#This Row],[Manufacturing_costs]] -> 9988.4354 | AD13: =supply_chain_data4[[#This Row],[Order_quantities]]*supply_chain_data4[[#This Row],[Shipping_costs]] -> 271.43659 | AE13: =supply_chain_data4[[#This Row],[Revenue_generated ]]-AC13-AD13 -> -4159.9279
... A101: haircare | B101: SKU99 | C101: 68.517833 | D101: 17 | E101: 627 | F101: 9185.1858 | G101: Unknown | H101: 55 | I101: 8 | J101: 59 | K101: 6 | L101: Carrier B | M101: 1.3110238 | N101: Supplier 2 | O101: Chennai | P101: 29 | Q101: 921 | R101: 2 | S101: 38.072899 | T101: Fail | U101: 0.34602729 | V101: Rail | W101: Route B | X101: 210.74301 | Y101: =supply_chain_data4[[#This Row],[Revenue_generated ]]/supply_chain_data4[[#This Row],[Number_of_products sold]] -> 14.649419 | Z101: =IF(supply_chain_data4[[#This Row],[Stock_levels]]<30,"Low Stock", IF(supply_chain_data4[[#This Row],[Stock_levels]]<=70,"Medium Stock","High Stock")) -> Medium Stock | AA101: =IF(supply_chain_data4[[#This Row],[Lead_time]]<=10,"Short", IF(supply_chain_data4[[#This Row],[Lead_time]]<=20,"Medium","Long")) -> Long | AB101: =IF(supply_chain_data4[[#This Row],[Defect_rates]]<2,"Low Defect", IF(supply_chain_data4[[#This Row],[Defect_rates]]<=4,"Medium Defect","High Defect")) -> Low Defect | AC101: =supply_chain_data4[[#This Row],[Production_volumes]]*supply_chain_data4[[#This Row],[Manufacturing_costs]] -> 35065.14 | AD101: =supply_chain_data4[[#This Row],[Order_quantities]]*supply_chain_data4[[#This Row],[Shipping_costs]] -> 77.350402 | AE101: =supply_chain_data4[[#This Row],[Revenue_generated ]]-AC101-AD101 -> -25957.304

Sheet Analysis
A3: Total_Revenue | B3: =SUM(Data_Cleaning!F2:F101) -> 577604.82
A4: Total Products Sold | B4: =SUM(Data_Cleaning!E2:E101) -> 46099
A5: Estimated Total Profit | B5: =SUM(Data_Cleaning!AE2:AE101) -> -2172598.4
A6: Lead_time | B6: =AVERAGE(Data_Cleaning!P2:P101) -> 17.08
A7: Average_Defect_Rate | B7: =AVERAGE(Data_Cleaning!U2:U101) -> 2.277158
A8: Total_Estimated_Shipping_Cost | B8: =SUM(Data_Cleaning!AD2:AD101) -> 27337.948
A9: Total_Production_Volume | B9: =SUM(Data_Cleaning!Q2:Q101) -> 56784
A10: Average_Manufacturing_Cost | B10: =AVERAGE(Data_Cleaning!S2:S101) -> 47.266693
A11: Average_Shipping_Time | B11: =AVERAGE(Data_Cleaning!K2:K101) -> 5.75

Sheet PT_Product_Revenue
A3: Row Labels | B3: Sum of Revenue_generated
A4: cosmetics | B4: 161521.27
A5: haircare | B5: 174455.39
A6: skincare | B6: 241628.16
A7: Grand Total | B7: 577604.82

Sheet PT_Product_Sales
A3: Row Labels | B3: Sum of Number_of_products sold
A4: cosmetics | B4: 11757
A5: haircare | B5: 13611
A6: skincare | B6: 20731
A7: Grand Total | B7: 46099

Sheet PT_Supplier_Revenue
A3: Row Labels | B3: Sum of Revenue_generated
A4: Supplier 1 | B4: 157529
A5: Supplier 2 | B5: 125467.42
A6: Supplier 5 | B6: 110343.46
A7: Supplier 3 | B7: 97795.98
A8: Supplier 4 | B8: 86468.962
A9: Grand Total | B9: 577604.82

Sheet PT_Supplier_LeadTime
A3: Row Labels | B3: Average of Lead_time
A4: Supplier 3 | B4: 20.133333
A5: Supplier 2 | B5: 18.545455
A6: Supplier 5 | B6: 18.055556
A7: Supplier 4 | B7: 15.222222
A8: Supplier 1 | B8: 14.777778
A9: Grand Total | B9: 17.08

Sheet PT_Transportation
A3: Row Labels | B3: Sum of Shipping_costs | C3: Average of Shipping_times
A4: Air | B4: 156.46382 | C4: 5.1153846
A5: Rail | B5: 153.13474 | C5: 6.5714286
A6: Road | B6: 160.72135 | C6: 4.7241379
A7: Sea | B7: 84.494995 | C7: 7.1176471
A8: Grand Total | B8: 554.81491 | C8: 5.75

Sheet PT_Inspection
A3: Row Labels | B3: Count of SKU
A4: Pending | B4: 41
A5: Fail | B5: 36
A6: Pass | B6: 23
A7: Grand Total | B7: 100

Sheet Top-_10_Product
A4: Row Labels | B4: Sum of Revenue_generated
A5: SKU51 | B5: 9866.4655
A6: SKU38 | B6: 9692.318
A7: SKU31 | B7: 9655.1351
A8: SKU90 | B8: 9592.6336
A9: SKU2 | B9: 9577.7496
A10: SKU32 | B10: 9571.5505
A11: SKU67 | B11: 9473.798
A12: SKU88 | B12: 9444.742
A13: SKU52 | B13: 9435.7626
A14: SKU18 | B14: 9364.6735
A15: Grand Total | B15: 95674.828

Sheet PT_Defect_Rate_Supplier
A3: Row Labels | B3: Average of Defect_rates
A4: Supplier 1 | B4: 1.8036297
A5: Supplier 2 | B5: 2.3627501
A6: Supplier 3 | B6: 2.465786
A7: Supplier 4 | B7: 2.3373974
A8: Supplier 5 | B8: 2.6654083
A9: Grand Total | B9: 2.277158

Sheet Dashboard
